app
locale
logs
templates
yogasoft
