Metadata-Version: 1.0
Name: yogasoft
Version: 1.5.2.dev0
Summary: yogasoft software
Home-page: https://yogasoft.codernetwork.ga
Author: codertarasvaskiv
Author-email: codertarasvaskiv@gmail.com
License: UNKNOWN
Keywords: python3
Platform: UNKNOWN
